ghi/__init__.py
ghi/cli.py
ghi/git/__init__.py
ghi/git/cli.py
ghi/git/orphan_branch.py
ghi/git/tests/__init__.py
ghi/git/tests/test_git_orphan_branch.py
ghi_cli-0.4.0.dist-info/METADATA
ghi_cli-0.4.0.dist-info/WHEEL
ghi_cli-0.4.0.dist-info/entry_points.txt
ghi_cli-0.4.0.dist-info/RECORD
