Metadata-Version: 2.4
Name: ghi-cli
Version: 0.4.0
Summary: 
Author: Gabriel Dornas
Author-email: gabrielbdornas@gmail.com
Requires-Python: >=3.13,<4.0
Classifier: Programming Language :: Python :: 3
Classifier: Programming Language :: Python :: 3.13
Classifier: Programming Language :: Python :: 3.14
Requires-Dist: python-dotenv[cli] (>=1.2.1,<2.0.0)
Requires-Dist: taskipy (>=1.14.1,<2.0.0)
